groupyr/__init__.py
groupyr/_base.py
groupyr/_prox.py
groupyr/_version.py
groupyr/datasets.py
groupyr/decomposition.py
groupyr/logistic.py
groupyr/sgl.py
groupyr/transform.py
groupyr/utils.py
groupyr/_copt/__init__.py
groupyr/_copt/loss.py
groupyr/_copt/proximal_gradient.py
groupyr/_copt/utils.py
groupyr/_copt/tests/test_proximal_gradient.py
groupyr/tests/__init__.py
groupyr/tests/test_common.py
groupyr/tests/test_datasets.py
groupyr/tests/test_decomposition.py
groupyr/tests/test_prox.py
groupyr/tests/test_sgl.py
groupyr/tests/test_transform.py
groupyr/tests/test_utils.py
groupyr-0.3.4.dist-info/LICENSE
groupyr-0.3.4.dist-info/METADATA
groupyr-0.3.4.dist-info/WHEEL
groupyr-0.3.4.dist-info/top_level.txt
groupyr-0.3.4.dist-info/RECORD
