Metadata-Version: 2.1
Name: groupyr
Version: 0.3.4
Summary: groupyr: Sparse Groups Lasso in Python
Home-page: https://richford.github.io/groupyr
Download-URL: https://github.com/richford/groupyr
Author: Adam Richie-Halford
Author-email: richiehalford@gmail.com
Maintainer: Adam Richie-Halford
Maintainer-email: richiehalford@gmail.com
License: BSD License
Platform: OS Independent
Classifier: Development Status :: 3 - Alpha
Classifier: Environment :: Console
Classifier: Intended Audience :: Science/Research
Classifier: License :: OSI Approved :: BSD License
Classifier: Operating System :: OS Independent
Classifier: Programming Language :: Python
Classifier: Topic :: Scientific/Engineering
Requires-Python: >=3.10
License-File: LICENSE
Requires-Dist: copt==0.9.1
Requires-Dist: scikit-learn>=1.0.0
Requires-Dist: scipy
Requires-Dist: scikit-optimize==0.9.0
Requires-Dist: tqdm
Requires-Dist: numpy>=1.22.4
Provides-Extra: all
Requires-Dist: scikit-fda>=0.9.1; extra == "all"
Requires-Dist: numba>=0.53; extra == "all"
Requires-Dist: black; extra == "all"
Requires-Dist: flake8; extra == "all"
Requires-Dist: matplotlib; extra == "all"
Requires-Dist: numpydoc; extra == "all"
Requires-Dist: pre-commit; extra == "all"
Requires-Dist: pydocstyle; extra == "all"
Requires-Dist: pytest-cov; extra == "all"
Requires-Dist: pytest-xdist[psutil]; extra == "all"
Requires-Dist: pytest; extra == "all"
Requires-Dist: sphinx; extra == "all"
Requires-Dist: sphinx-gallery; extra == "all"
Requires-Dist: sphinx-panels; extra == "all"
Requires-Dist: sphinx-rtd-theme; extra == "all"
Requires-Dist: tox; extra == "all"
Requires-Dist: rapidfuzz; extra == "all"
Provides-Extra: dev
Requires-Dist: black; extra == "dev"
Requires-Dist: flake8; extra == "dev"
Requires-Dist: matplotlib; extra == "dev"
Requires-Dist: numpydoc; extra == "dev"
Requires-Dist: pre-commit; extra == "dev"
Requires-Dist: pydocstyle; extra == "dev"
Requires-Dist: pytest-cov; extra == "dev"
Requires-Dist: pytest-xdist[psutil]; extra == "dev"
Requires-Dist: pytest; extra == "dev"
Requires-Dist: sphinx; extra == "dev"
Requires-Dist: sphinx-gallery; extra == "dev"
Requires-Dist: sphinx-panels; extra == "dev"
Requires-Dist: sphinx-rtd-theme; extra == "dev"
Requires-Dist: tox; extra == "dev"
Provides-Extra: fda
Requires-Dist: scikit-fda>=0.9.1; extra == "fda"
Requires-Dist: numba>=0.53; extra == "fda"
Provides-Extra: maint
Requires-Dist: rapidfuzz; extra == "maint"
